{
    "display": {
        "icon": {
            "item": "minecraft:golden_hoe",
            "nbt": "{CustomModelData:20200,HideFlags:39}"
        },
        "title": {"translate":"advancements.galaxy.katana_obtain.title"},
        "description": {"translate":"advancements.galaxy.katana_obtain.description"}
    },
    "parent": "galaxy:root",
    "rewards": {
		"function": "galaxy:advancement/weaponry/katana"
    },
    "criteria": {
        "katana": {
            "trigger": "minecraft:inventory_changed",
            "conditions": {
                "items": [
                    {
                        "nbt": "{katana:1}"
                    }
                ]
            }
        }
    }
}