{
    "display": {
        "icon": {
            "item": "minecraft:diamond_hoe",
            "nbt": "{CustomModelData:1400075,HideFlags:127}"
        },
        "title": {"translate":"advancements.weaponry.collections"},
        "description": {"translate":"advancements.weaponry.collections.description"},
		"hidden": true,
		"frame": "challenge",
        "show_toast": false,
        "announce_to_chat": false
    },
    "parent": "galaxy:weaponry/gun",
    "criteria": {
        "gun_collections": {
            "trigger": "minecraft:impossible"
        }
    }
}