{
  "display": {
    "icon": {"item": "minecraft:barrier"},
    "title": {"text":"interacted_with_entity_interaction"},
    "description": {"text":""},
    "background": "minecraft:textures/block/command_block_back.png",
    "show_toast": false,
    "announce_to_chat": false
  },
  "criteria": {
    "interacted_with_entity_interaction": {
      "trigger": "minecraft:player_interacted_with_entity",
      "conditions": {
        "entity": {
          "type": "minecraft:interaction",
          "nbt": "{Tags:[\"galaxy.entity_interaction\"]}"
        }
      }
    }
  },
  "rewards": {
    "function": "galaxy:trigger/interacted_with_entity_interaction"
  }
}